Metadata-Version: 2.1
Name: ofxstatement-ly-bsic
Version: 1.1.0
Summary: OFXStatement plugin for BSIC ()
Home-page: https://github.com/EtsBiz4Africa/ofxstatement-ly-bsic
Download-URL: https://github.com/EtsBiz4Africa/ofxstatement-ly-bsic/archive/v1.1.0.zip
Author: Vincent Luba
Author-email: vincent@biz-4-africa.com
License: GPLv3
Keywords: ofx,banking,statement
Classifier: Development Status :: 4 - Beta
Classifier: Programming Language :: Python :: 3
Classifier: Natural Language :: English
Classifier: Topic :: Office/Business :: Financial :: Accounting
Classifier: Topic :: Utilities
Classifier: Environment :: Console
Classifier: Operating System :: OS Independent
Classifier: License :: OSI Approved :: GNU Affero General Public License v3
Provides-Extra: test
License-File: LICENSE
